trove_newspaper_images/__init__.py
trove_newspaper_images/_modidx.py
trove_newspaper_images/_nbdev.py
trove_newspaper_images/articles.py
trove_newspaper_images-0.3.1.dist-info/LICENSE
trove_newspaper_images-0.3.1.dist-info/METADATA
trove_newspaper_images-0.3.1.dist-info/WHEEL
trove_newspaper_images-0.3.1.dist-info/entry_points.txt
trove_newspaper_images-0.3.1.dist-info/top_level.txt
trove_newspaper_images-0.3.1.dist-info/RECORD
