Metadata-Version: 2.1
Name: trove-newspaper-images
Version: 0.3.1
Summary: Tool to download Trove newspaper articles as images.
Home-page: https://github.com/wragge/trove_newspaper_images
Author: Tim Sherratt
Author-email: tim@timsherratt.org
License: MIT License
Keywords: nbdev jupyter notebook python
Classifier: Development Status :: 4 - Beta
Classifier: Intended Audience :: Developers
Classifier: Natural Language :: English
Classifier: Programming Language :: Python :: 3.8
Classifier: Programming Language :: Python :: 3.9
Classifier: Programming Language :: Python :: 3.10
Classifier: License :: OSI Approved :: MIT License
Requires-Python: >=3.8
License-File: LICENSE
Requires-Dist: requests
Requires-Dist: beautifulsoup4
Requires-Dist: lxml
Requires-Dist: pillow
Provides-Extra: dev
Requires-Dist: jupyterlab ; extra == 'dev'
Requires-Dist: nbdev ; extra == 'dev'
Requires-Dist: jupyterlab-code-formatter ; extra == 'dev'
Requires-Dist: black ; extra == 'dev'
Requires-Dist: isort ; extra == 'dev'
